setup.py
mpls/__init__.py
mpls/cache.py
mpls/config.py
mpls/mpls.py
mpls/utils.py
mpls/version.py
mpls.egg-info/PKG-INFO
mpls.egg-info/SOURCES.txt
mpls.egg-info/dependency_links.txt
mpls.egg-info/not-zip-safe
mpls.egg-info/requires.txt
mpls.egg-info/top_level.txt