Metadata-Version: 1.1
Name: mpls
Version: 0.2.0
Summary: An open library of matplotlib styles
Home-page: https://github.com/scruffy-t/mpls
Author: Tobias Schruff
Author-email: tobias.schruff@gmail.com
License: BSD (3-clause)
Download-URL: https://github.com/scruffy-t/mpls/archive/0.2.0.tar.gz
Keywords: plotting matplotlib styles
Platform: UNKNOWN
Classifier: Development Status :: 4 - Beta
Classifier: License :: OSI Approved :: BSD License
Classifier: Programming Language :: Python :: 3
Classifier: Programming Language :: Python :: 3.2
Classifier: Programming Language :: Python :: 3.3
Classifier: Programming Language :: Python :: 3.4
Classifier: Programming Language :: Python :: 3.5
Classifier: Programming Language :: Python :: 3.6
